easyautoml/__init__.py
easyautoml/command_line.py
easyautoml/ftutils.py
easyautoml/tpotutils.py
easyautoml/utils.py
easyautoml-0.1.dist-info/METADATA
easyautoml-0.1.dist-info/RECORD
easyautoml-0.1.dist-info/WHEEL
easyautoml-0.1.dist-info/entry_points.txt
easyautoml-0.1.dist-info/top_level.txt
